validator_entrypoint.py
validator_devel/__init__.py
validator_devel/__main__.py
validator_devel/filesystem.py
validator_devel/main.py
validator_devel/routes.py
validator_devel/templating.py
validator_devel/views.py
validator_devel/config/config.yaml
validator_devel/config/settings_template.yaml
validator_devel/static/asset-manifest.json
validator_devel/static/favicon.ico
validator_devel/static/index.html
validator_devel/static/manifest.json
validator_devel/static/precache-manifest.f4a652c193d11adef3d80d4bcb9a00ef.js
validator_devel/static/service-worker.js
validator_devel/static/static/css/main.60e61851.chunk.css
validator_devel/static/static/css/main.60e61851.chunk.css.map
validator_devel/static/static/js/1.a4518149.chunk.js
validator_devel/static/static/js/1.a4518149.chunk.js.map
validator_devel/static/static/js/main.b3e8b4d1.chunk.js
validator_devel/static/static/js/main.b3e8b4d1.chunk.js.map
validator_devel/static/static/js/runtime~main.229c360f.js
validator_devel/static/static/js/runtime~main.229c360f.js.map
validator_devel-2.0.12.dist-info/LICENSE
validator_devel-2.0.12.dist-info/METADATA
validator_devel-2.0.12.dist-info/WHEEL
validator_devel-2.0.12.dist-info/entry_points.txt
validator_devel-2.0.12.dist-info/top_level.txt
validator_devel-2.0.12.dist-info/RECORD
