Metadata-Version: 2.1
Name: validator-devel
Version: 2.0.12
Summary: Utility manager for handle globo modules.
Home-page: UNKNOWN
Author: Mattia Rossi
Author-email: UNKNOWN
License: UNKNOWN
Platform: UNKNOWN
Classifier: Programming Language :: Python :: 3
Classifier: License :: OSI Approved :: MIT License
Classifier: Operating System :: OS Independent
Requires-Dist: PyYAML
Requires-Dist: argh
Requires-Dist: pathtools
Requires-Dist: aiohttp
Requires-Dist: watchdog
Requires-Dist: Jinja2
Requires-Dist: dynaconf
